socha-4.3.4.dist-info/METADATA
socha-4.3.4.dist-info/WHEEL
socha-4.3.4.dist-info/licenses/LICENSE
socha/utils/package_builder.py
socha/_socha.pyi
socha/api/__init__.py
socha/api/protocol/__init__.py
socha/api/protocol/room_message.py
socha/api/protocol/protocol_packet.py
socha/api/protocol/protocol.py
socha/api/networking/utils.py
socha/api/networking/network_socket.py
socha/api/networking/__init__.py
socha/api/networking/xml_protocol_interface.py
socha/api/networking/game_client.py
socha/starter.py
socha/__init__.py
socha/py.typed
socha/_socha.cpython-312-x86_64-linux-gnu.so
socha-4.3.4.dist-info/RECORD
