Metadata-Version: 2.4
Name: socha
Version: 4.3.4
Classifier: License :: OSI Approved :: MIT License
Classifier: Operating System :: MacOS
Classifier: Operating System :: Microsoft :: Windows
Classifier: Operating System :: POSIX :: Linux
Classifier: Programming Language :: Python :: 3
Classifier: Programming Language :: Python :: 3.10
Classifier: Programming Language :: Python :: 3.11
Classifier: Programming Language :: Python :: 3.12
Classifier: Programming Language :: Python :: 3.13
Classifier: Programming Language :: Python :: Implementation :: CPython
Classifier: Programming Language :: Python
Classifier: Programming Language :: Rust
Classifier: Typing :: Typed
Requires-Dist: xsdata ==22.9
License-File: LICENSE
Summary: Dieses Paket ist für die Software-Challenge Germany 2026, bei der in dieser Saison das Spiel 'Piranhas' im Mittelpunkt steht.
Author-email: yoente <stu250140@mail.uni-kiel.de>, maxblan <stu222782@mail.uni-kiel.de>
Requires-Python: >=3.10
Project-URL: homepage, https://software-challenge.de/
Project-URL: repository, https://github.com/software-challenge/player_python
Project-URL: documentation, https://socha-python-client.readthedocs.io/de/latest/
Project-URL: bug-tracker, https://github.com/software-challenge/player_python/issues
